{
  "category_counts": {
    "PADRAO_FRACO": 12,
    "FORCA_INSUFICIENTE": 1,
    "CONTRA_TENDENCIA": 5,
    "VOLATILIDADE_ALTA": 1
  },
  "losses": [
    {
      "timestamp": "2026-02-04T15:48:01.795528",
      "ativo": "GBPJPY-OTC",
      "direcao": "CALL",
      "preco_entrada": 215.149745,
      "preco_saida": 215.14964500356555,
      "prejuizo": -86.94,
      "tendencia_m1": "ALTA",
      "tendencia_forca": 1.0,
      "estrutura": "RANGE",
      "tinha_pullback": false,
      "pullback_depth": 0.0,
      "vela_tipo": "vermelha",
      "vela_tamanho_atr": 1.0392139480952973,
      "vela_pavio_sup": 0.21333715486764981,
      "vela_pavio_inf": 0.12200248399735776,
      "proximo_sr": "NONE",
      "distancia_sr": 0.0,
      "sr_foi_rompido": false,
      "atr_valor": 0.20144071428571766,
      "volatilidade": "alta",
      "agentes_votos": {},
      "consenso": 0,
      "categoria_loss": "PADRAO_FRACO",
      "motivo_detalhado": "Entrou CALL mas vela era vermelha",
      "licao_aprendida": "Esperar vela de confirmacao na direcao antes de entrar."
    },
    {
      "timestamp": "2026-02-04T16:43:02.022623",
      "ativo": "EURJPY-OTC",
      "direcao": "CALL",
      "preco_entrada": 184.902845,
      "preco_saida": 184.9027450041825,
      "prejuizo": -86.07,
      "tendencia_m1": "ALTA",
      "tendencia_forca": 0.9250979502863554,
      "estrutura": "RANGE",
      "tinha_pullback": false,
      "pullback_depth": 0.0,
      "vela_tipo": "vermelha",
      "vela_tamanho_atr": 0.7046391300533472,
      "vela_pavio_sup": 0.31051649035464296,
      "vela_pavio_inf": 0.2820161792160189,
      "proximo_sr": "NONE",
      "distancia_sr": 0.0,
      "sr_foi_rompido": false,
      "atr_valor": 0.1140299999999976,
      "volatilidade": "alta",
      "agentes_votos": {},
      "consenso": 0,
      "categoria_loss": "PADRAO_FRACO",
      "motivo_detalhado": "Entrou CALL mas vela era vermelha",
      "licao_aprendida": "Esperar vela de confirmacao na direcao antes de entrar."
    },
    {
      "timestamp": "2026-02-04T17:13:01.425131",
      "ativo": "GBPJPY-OTC",
      "direcao": "PUT",
      "preco_entrada": 214.563505,
      "preco_saida": 214.56340500340323,
      "prejuizo": -85.21,
      "tendencia_m1": "BAIXA",
      "tendencia_forca": 0.9277119734606425,
      "estrutura": "RANGE",
      "tinha_pullback": false,
      "pullback_depth": 0.0,
      "vela_tipo": "vermelha",
      "vela_tamanho_atr": 1.0083919446490008,
      "vela_pavio_sup": 0.16424711242983267,
      "vela_pavio_inf": 0.5222528345872492,
      "proximo_sr": "NONE",
      "distancia_sr": 0.0,
      "sr_foi_rompido": false,
      "atr_valor": 0.18716928571428834,
      "volatilidade": "alta",
      "agentes_votos": {},
      "consenso": 0,
      "categoria_loss": "PADRAO_FRACO",
      "motivo_detalhado": "PUT mas pavio inferior grande (52%) - rejeicao de baixa",
      "licao_aprendida": "Pavio inferior grande indica rejeicao. Nao entrar PUT."
    },
    {
      "timestamp": "2026-02-04T17:48:01.437199",
      "ativo": "GBPJPY-OTC",
      "direcao": "PUT",
      "preco_entrada": 214.139385,
      "preco_saida": 214.13928500136285,
      "prejuizo": -88.05,
      "tendencia_m1": "BAIXA",
      "tendencia_forca": 0.9412459206171566,
      "estrutura": "RANGE",
      "tinha_pullback": false,
      "pullback_depth": 0.0,
      "vela_tipo": "vermelha",
      "vela_tamanho_atr": 1.587962747844253,
      "vela_pavio_sup": 0.16538405267001982,
      "vela_pavio_inf": 0.03359180687638991,
      "proximo_sr": "NONE",
      "distancia_sr": 0.0,
      "sr_foi_rompido": false,
      "atr_valor": 0.21521285714286112,
      "volatilidade": "alta",
      "agentes_votos": {},
      "consenso": 0,
      "categoria_loss": "FORCA_INSUFICIENTE",
      "motivo_detalhado": "Apenas 0/5 agentes concordaram",
      "licao_aprendida": "Exigir consenso de 4+ agentes para maior probabilidade."
    },
    {
      "timestamp": "2026-02-04T17:53:02.109450",
      "ativo": "GBPJPY-OTC",
      "direcao": "PUT",
      "preco_entrada": 214.201275,
      "preco_saida": 214.20117500080303,
      "prejuizo": -87.17,
      "tendencia_m1": "BAIXA",
      "tendencia_forca": 0.8981281155140857,
      "estrutura": "RANGE",
      "tinha_pullback": false,
      "pullback_depth": 0.0,
      "vela_tipo": "verde",
      "vela_tamanho_atr": 0.8232437930402201,
      "vela_pavio_sup": 0.2649577496738588,
      "vela_pavio_inf": 0.3898372369987429,
      "proximo_sr": "NONE",
      "distancia_sr": 0.0,
      "sr_foi_rompido": false,
      "atr_valor": 0.2141892857142896,
      "volatilidade": "alta",
      "agentes_votos": {},
      "consenso": 0,
      "categoria_loss": "PADRAO_FRACO",
      "motivo_detalhado": "Entrou PUT mas vela era verde",
      "licao_aprendida": "Esperar vela de confirmacao na direcao antes de entrar."
    },
    {
      "timestamp": "2026-02-04T17:58:01.937546",
      "ativo": "GBPJPY-OTC",
      "direcao": "PUT",
      "preco_entrada": 214.255015,
      "preco_saida": 214.25491499872535,
      "prejuizo": -86.3,
      "tendencia_m1": "BAIXA",
      "tendencia_forca": 0.8218878077611582,
      "estrutura": "RANGE",
      "tinha_pullback": false,
      "pullback_depth": 0.0,
      "vela_tipo": "verde",
      "vela_tamanho_atr": 0.7806621834464307,
      "vela_pavio_sup": 0.5425487256372199,
      "vela_pavio_inf": 0.13079460269874263,
      "proximo_sr": "NONE",
      "distancia_sr": 0.0,
      "sr_foi_rompido": false,
      "atr_valor": 0.21360071428572017,
      "volatilidade": "alta",
      "agentes_votos": {},
      "consenso": 0,
      "categoria_loss": "PADRAO_FRACO",
      "motivo_detalhado": "Entrou PUT mas vela era verde",
      "licao_aprendida": "Esperar vela de confirmacao na direcao antes de entrar."
    },
    {
      "timestamp": "2026-02-04T18:03:01.252925",
      "ativo": "GBPJPY-OTC",
      "direcao": "PUT",
      "preco_entrada": 214.343515,
      "preco_saida": 214.34341499531814,
      "prejuizo": -85.44,
      "tendencia_m1": "ALTA",
      "tendencia_forca": 0.8589594712291881,
      "estrutura": "RANGE",
      "tinha_pullback": false,
      "pullback_depth": 0.0,
      "vela_tipo": "verde",
      "vela_tamanho_atr": 0.6342619083471291,
      "vela_pavio_sup": 0.26279636605369594,
      "vela_pavio_inf": 0.0893714454539012,
      "proximo_sr": "NONE",
      "distancia_sr": 0.0,
      "sr_foi_rompido": false,
      "atr_valor": 0.21346071428571836,
      "volatilidade": "alta",
      "agentes_votos": {},
      "consenso": 0,
      "categoria_loss": "CONTRA_TENDENCIA",
      "motivo_detalhado": "Entrada PUT contra tendencia ALTA",
      "licao_aprendida": "Operar somente NA DIRECAO da tendencia. LH+LL=PUT, HH+HL=CALL."
    },
    {
      "timestamp": "2026-02-07T10:17:01.893593",
      "ativo": "USDCHF-OTC",
      "direcao": "PUT",
      "preco_entrada": 0.760705,
      "preco_saida": 0.7606050038029184,
      "prejuizo": -97.29,
      "tendencia_m1": "BAIXA",
      "tendencia_forca": 0.8085432452502892,
      "estrutura": "RANGE",
      "tinha_pullback": false,
      "pullback_depth": 0.0,
      "vela_tipo": "vermelha",
      "vela_tamanho_atr": 0.843971631205711,
      "vela_pavio_sup": 0.23529411764663624,
      "vela_pavio_inf": 0.5882352941175703,
      "proximo_sr": "NONE",
      "distancia_sr": 0.0,
      "sr_foi_rompido": false,
      "atr_valor": 0.00020142857142856668,
      "volatilidade": "baixa",
      "agentes_votos": {},
      "consenso": 0,
      "categoria_loss": "PADRAO_FRACO",
      "motivo_detalhado": "PUT mas pavio inferior grande (59%) - rejeicao de baixa",
      "licao_aprendida": "Pavio inferior grande indica rejeicao. Nao entrar PUT."
    },
    {
      "timestamp": "2026-02-07T10:18:01.854741",
      "ativo": "USDSGD-OTC",
      "direcao": "CALL",
      "preco_entrada": 1.273495,
      "preco_saida": 1.273395000830558,
      "prejuizo": -96.32,
      "tendencia_m1": "ALTA",
      "tendencia_forca": 0.847552238688656,
      "estrutura": "RANGE",
      "tinha_pullback": false,
      "pullback_depth": 0.0,
      "vela_tipo": "vermelha",
      "vela_tamanho_atr": 5.526822558459201,
      "vela_pavio_sup": 0.08362369337972193,
      "vela_pavio_inf": 0.06271777003486881,
      "proximo_sr": "NONE",
      "distancia_sr": 0.0,
      "sr_foi_rompido": false,
      "atr_valor": 0.0005192857142857221,
      "volatilidade": "normal",
      "agentes_votos": {},
      "consenso": 0,
      "categoria_loss": "VOLATILIDADE_ALTA",
      "motivo_detalhado": "Vela muito grande (5.5x ATR) - mercado instavel",
      "licao_aprendida": "Evitar velas > 1.5x ATR. Mercado muito volatil para operar."
    },
    {
      "timestamp": "2026-02-07T10:19:01.458635",
      "ativo": "EURUSD-OTC",
      "direcao": "PUT",
      "preco_entrada": 1.165725,
      "preco_saida": 1.165624997483158,
      "prejuizo": -95.36,
      "tendencia_m1": "LATERAL",
      "tendencia_forca": 0.5,
      "estrutura": "RANGE",
      "tinha_pullback": false,
      "pullback_depth": 0.0,
      "vela_tipo": "verde",
      "vela_tamanho_atr": 0.8789808917198242,
      "vela_pavio_sup": 0.028985507246563364,
      "vela_pavio_inf": 0.2318840579708979,
      "proximo_sr": "NONE",
      "distancia_sr": 0.0,
      "sr_foi_rompido": false,
      "atr_valor": 0.0007850000000000198,
      "volatilidade": "normal",
      "agentes_votos": {},
      "consenso": 0,
      "categoria_loss": "PADRAO_FRACO",
      "motivo_detalhado": "Entrou PUT mas vela era verde",
      "licao_aprendida": "Esperar vela de confirmacao na direcao antes de entrar."
    },
    {
      "timestamp": "2026-02-07T10:23:01.355080",
      "ativo": "GBPUSD-OTC",
      "direcao": "CALL",
      "preco_entrada": 1.364745,
      "preco_saida": 1.364645,
      "prejuizo": -93.46,
      "tendencia_m1": "BAIXA",
      "tendencia_forca": 0.8953884925529896,
      "estrutura": "RANGE",
      "tinha_pullback": false,
      "pullback_depth": 0.0,
      "vela_tipo": "vermelha",
      "vela_tamanho_atr": 0.012075279612007717,
      "vela_pavio_sup": 0.0,
      "vela_pavio_inf": 0.2622950819674757,
      "proximo_sr": "NONE",
      "distancia_sr": 0.0,
      "sr_foi_rompido": false,
      "atr_valor": 0.05051642857142724,
      "volatilidade": "alta",
      "agentes_votos": {},
      "consenso": 0,
      "categoria_loss": "CONTRA_TENDENCIA",
      "motivo_detalhado": "Entrada CALL contra tendencia BAIXA",
      "licao_aprendida": "Operar somente NA DIRECAO da tendencia. LH+LL=PUT, HH+HL=CALL."
    },
    {
      "timestamp": "2026-02-07T10:28:01.395617",
      "ativo": "USDHKD-OTC",
      "direcao": "CALL",
      "preco_entrada": 7.837545,
      "preco_saida": 7.837444999582244,
      "prejuizo": -95.75,
      "tendencia_m1": "BAIXA",
      "tendencia_forca": 0.8646048992102479,
      "estrutura": "RANGE",
      "tinha_pullback": false,
      "pullback_depth": 0.0,
      "vela_tipo": "vermelha",
      "vela_tamanho_atr": 0.82033020394943,
      "vela_pavio_sup": 0.09392265193358779,
      "vela_pavio_inf": 0.07182320442011994,
      "proximo_sr": "NONE",
      "distancia_sr": 0.0,
      "sr_foi_rompido": false,
      "atr_valor": 0.002206428571428593,
      "volatilidade": "alta",
      "agentes_votos": {},
      "consenso": 0,
      "categoria_loss": "CONTRA_TENDENCIA",
      "motivo_detalhado": "Entrada CALL contra tendencia BAIXA",
      "licao_aprendida": "Operar somente NA DIRECAO da tendencia. LH+LL=PUT, HH+HL=CALL."
    },
    {
      "timestamp": "2026-02-07T10:29:01.231281",
      "ativo": "USDZAR-OTC",
      "direcao": "PUT",
      "preco_entrada": 16.077345,
      "preco_saida": 16.077245002215374,
      "prejuizo": -94.79,
      "tendencia_m1": "ALTA",
      "tendencia_forca": 0.7765420941121058,
      "estrutura": "RANGE",
      "tinha_pullback": false,
      "pullback_depth": 0.0,
      "vela_tipo": "verde",
      "vela_tamanho_atr": 18.210268948658857,
      "vela_pavio_sup": 0.10526315789473684,
      "vela_pavio_inf": 0.22744360902258023,
      "proximo_sr": "NONE",
      "distancia_sr": 0.0,
      "sr_foi_rompido": false,
      "atr_valor": 0.00029214285714285985,
      "volatilidade": "baixa",
      "agentes_votos": {},
      "consenso": 0,
      "categoria_loss": "CONTRA_TENDENCIA",
      "motivo_detalhado": "Entrada PUT contra tendencia ALTA",
      "licao_aprendida": "Operar somente NA DIRECAO da tendencia. LH+LL=PUT, HH+HL=CALL."
    },
    {
      "timestamp": "2026-02-07T11:41:01.736351",
      "ativo": "EURGBP-OTC",
      "direcao": "CALL",
      "preco_entrada": 0.867995,
      "preco_saida": 0.8678949961572934,
      "prejuizo": -96.29,
      "tendencia_m1": "LATERAL",
      "tendencia_forca": 0.5,
      "estrutura": "RANGE",
      "tinha_pullback": false,
      "pullback_depth": 0.0,
      "vela_tipo": "vermelha",
      "vela_tamanho_atr": 1.4842406876790117,
      "vela_pavio_sup": 0.0,
      "vela_pavio_inf": 0.1621621621620324,
      "proximo_sr": "NONE",
      "distancia_sr": 0.0,
      "sr_foi_rompido": false,
      "atr_valor": 0.00024928571428571377,
      "volatilidade": "baixa",
      "agentes_votos": {},
      "consenso": 0,
      "categoria_loss": "PADRAO_FRACO",
      "motivo_detalhado": "Entrou CALL mas vela era vermelha",
      "licao_aprendida": "Esperar vela de confirmacao na direcao antes de entrar."
    },
    {
      "timestamp": "2026-02-07T11:47:01.911005",
      "ativo": "EURGBP-OTC",
      "direcao": "PUT",
      "preco_entrada": 0.868365,
      "preco_saida": 0.8682650035668052,
      "prejuizo": -95.32,
      "tendencia_m1": "LATERAL",
      "tendencia_forca": 0.5,
      "estrutura": "RANGE",
      "tinha_pullback": false,
      "pullback_depth": 0.0,
      "vela_tipo": "verde",
      "vela_tamanho_atr": 0.7621776504298708,
      "vela_pavio_sup": 0.052631578947122386,
      "vela_pavio_inf": 0.0,
      "proximo_sr": "NONE",
      "distancia_sr": 0.0,
      "sr_foi_rompido": false,
      "atr_valor": 0.00024928571428572174,
      "volatilidade": "baixa",
      "agentes_votos": {},
      "consenso": 0,
      "categoria_loss": "PADRAO_FRACO",
      "motivo_detalhado": "Entrou PUT mas vela era verde",
      "licao_aprendida": "Esperar vela de confirmacao na direcao antes de entrar."
    },
    {
      "timestamp": "2026-02-07T12:01:01.438638",
      "ativo": "EURUSD-OTC",
      "direcao": "CALL",
      "preco_entrada": 1.161995,
      "preco_saida": 1.1618949962537395,
      "prejuizo": -93.43,
      "tendencia_m1": "BAIXA",
      "tendencia_forca": 0.8412741679600704,
      "estrutura": "RANGE",
      "tinha_pullback": false,
      "pullback_depth": 0.0,
      "vela_tipo": "vermelha",
      "vela_tamanho_atr": 0.9310761789602321,
      "vela_pavio_sup": 0.10909090909080632,
      "vela_pavio_inf": 0.18181818181814513,
      "proximo_sr": "NONE",
      "distancia_sr": 0.0,
      "sr_foi_rompido": false,
      "atr_valor": 0.000590714285714254,
      "volatilidade": "normal",
      "agentes_votos": {},
      "consenso": 0,
      "categoria_loss": "CONTRA_TENDENCIA",
      "motivo_detalhado": "Entrada CALL contra tendencia BAIXA",
      "licao_aprendida": "Operar somente NA DIRECAO da tendencia. LH+LL=PUT, HH+HL=CALL."
    },
    {
      "timestamp": "2026-02-07T13:54:01.232724",
      "ativo": "AUDCAD-OTC",
      "direcao": "CALL",
      "preco_entrada": 0.963105,
      "preco_saida": 0.9630049991570002,
      "prejuizo": -94.9,
      "tendencia_m1": "ALTA",
      "tendencia_forca": 0.8452072518667497,
      "estrutura": "RANGE",
      "tinha_pullback": false,
      "pullback_depth": 0.0,
      "vela_tipo": "vermelha",
      "vela_tamanho_atr": 0.6197916666666867,
      "vela_pavio_sup": 0.23529411764728933,
      "vela_pavio_inf": 0.2941176470587851,
      "proximo_sr": "NONE",
      "distancia_sr": 0.0,
      "sr_foi_rompido": false,
      "atr_valor": 0.000274285714285711,
      "volatilidade": "baixa",
      "agentes_votos": {},
      "consenso": 0,
      "categoria_loss": "PADRAO_FRACO",
      "motivo_detalhado": "Entrou CALL mas vela era vermelha",
      "licao_aprendida": "Esperar vela de confirmacao na direcao antes de entrar."
    },
    {
      "timestamp": "2026-02-07T13:58:01.248393",
      "ativo": "AUDCAD-OTC",
      "direcao": "CALL",
      "preco_entrada": 0.963085,
      "preco_saida": 0.9629850003193178,
      "prejuizo": -93.95,
      "tendencia_m1": "ALTA",
      "tendencia_forca": 0.8171383166018323,
      "estrutura": "RANGE",
      "tinha_pullback": false,
      "pullback_depth": 0.0,
      "vela_tipo": "vermelha",
      "vela_tamanho_atr": 0.5185185185182292,
      "vela_pavio_sup": 0.4285714285713153,
      "vela_pavio_inf": 0.28571428571394586,
      "proximo_sr": "NONE",
      "distancia_sr": 0.0,
      "sr_foi_rompido": false,
      "atr_valor": 0.00026999999999999247,
      "volatilidade": "baixa",
      "agentes_votos": {},
      "consenso": 0,
      "categoria_loss": "PADRAO_FRACO",
      "motivo_detalhado": "Entrou CALL mas vela era vermelha",
      "licao_aprendida": "Esperar vela de confirmacao na direcao antes de entrar."
    },
    {
      "timestamp": "2026-02-07T14:06:01.225591",
      "ativo": "AUDCAD-OTC",
      "direcao": "CALL",
      "preco_entrada": 0.963175,
      "preco_saida": 0.9630750008601152,
      "prejuizo": -93.01,
      "tendencia_m1": "ALTA",
      "tendencia_forca": 0.8020765520929071,
      "estrutura": "RANGE",
      "tinha_pullback": false,
      "pullback_depth": 0.0,
      "vela_tipo": "vermelha",
      "vela_tamanho_atr": 0.7977207977206816,
      "vela_pavio_sup": 0.399999999999889,
      "vela_pavio_inf": 0.14999999999988897,
      "proximo_sr": "NONE",
      "distancia_sr": 0.0,
      "sr_foi_rompido": false,
      "atr_valor": 0.0002507142857142946,
      "volatilidade": "baixa",
      "agentes_votos": {},
      "consenso": 0,
      "categoria_loss": "PADRAO_FRACO",
      "motivo_detalhado": "Entrou CALL mas vela era vermelha",
      "licao_aprendida": "Esperar vela de confirmacao na direcao antes de entrar."
    }
  ],
  "last_updated": "2026-02-07T14:06:01.225826"
}